{
    "2025-01-01": [
        {
            "image": "sobrevivendo-no-inferno_racionais-mc's.jpg",
            "rym": "https://rateyourmusic.com/release/album/racionais-mcs/sobrevivendo-no-inferno/",
            "artist": "Racionais MC's",
            "album": "Sobrevivendo no inferno"
        }
    ],
    "2025-01-02": [
        {
            "image": "hbo-(haitian-body-odor)_mach-hommy.jpg",
            "rym": "https://rateyourmusic.com/release/album/mach-hommy/hbo-haitian-body-odor/",
            "artist": "Mach-Hommy",
            "album": "HBO (Haitian Body Odor)"
        },
        {
            "image": "beloved-paradise-jazz_mckinley-dixon.jpg",
            "rym": "https://rateyourmusic.com/release/album/mckinley-dixon/beloved-paradise-jazz/",
            "artist": "McKinley Dixon",
            "album": "Beloved! Paradise! Jazz!?"
        }
    ],
    "2025-01-03": [
        {
            "image": "orpheus-vs-the-sirens_hermit-and-the-recluse.jpg",
            "rym": "https://rateyourmusic.com/release/album/hermit-and-the-recluse/orpheus-vs-the-sirens/",
            "artist": "Hermit and the Recluse",
            "album": "Orpheus vs. the Sirens"
        },
        {
            "image": "ghost-tropic_songs:-ohia.jpg",
            "rym": "https://rateyourmusic.com/release/album/songs-ohia/ghost-tropic/",
            "artist": "Songs: Ohia",
            "album": "Ghost Tropic"
        }
    ],
    "2025-01-04": [
        {
            "image": "realms-of-chaos_bolt-thrower.jpg",
            "rym": "https://rateyourmusic.com/release/album/bolt-thrower/realm-of-chaos/",
            "artist": "Bolt Thrower",
            "album": "Realms of Chaos"
        }
    ],
    "2025-01-05": [
        {
            "image": "translating-the-name_saosin.jpg",
            "rym": "https://rateyourmusic.com/release/ep/saosin/translating-the-name/",
            "artist": "Saosin",
            "album": "Translating the Name"
        }
    ],
    "2025-01-06": [
        {
            "image": "i-can-tell-you-about-pain_converge.jpg",
            "rym": "https://rateyourmusic.com/release/ep/converge/i-can-tell-you-about-pain/",
            "artist": "Converge",
            "album": "I Can Tell You About Pain"
        }
    ],
    "2025-01-07": [
        {
            "image": "ultra-ego_feed-me-jack.jpg",
            "rym": "https://rateyourmusic.com/release/ep/feed-me-jack/ultra-ego/",
            "artist": "Feed Me Jack",
            "album": "Ultra Ego"
        }
    ],
    "2025-01-08": [
        {
            "image": "despise-the-sun_suffocation.jpg",
            "rym": "https://rateyourmusic.com/release/ep/suffocation/despise-the-sun/",
            "artist": "Suffocation",
            "album": "Despise the Sun"
        }
    ],
    "2025-01-09": [
        {
            "image": "alturas-de-machu-pichu_los-jaivas.jpg",
            "rym": "https://rateyourmusic.com/release/album/los-jaivas/alturas-de-machu-pichu/",
            "artist": "Los Jaivas",
            "album": "Alturas de Machu Pichu "
        },
        {
            "image": "pierced-from-within_suffocation.jpg",
            "rym": "https://rateyourmusic.com/release/album/suffocation/pierced-from-within/",
            "artist": "Suffocation",
            "album": "Pierced From Within"
        }
    ],
    "2025-01-10": [
        {
            "image": "nervous-breakdown_black-flag.jpg",
            "rym": "https://rateyourmusic.com/release/ep/black-flag/nervous-breakdown/",
            "artist": "Black Flag",
            "album": "Nervous Breakdown "
        }
    ],
    "2025-01-11": [
        {
            "image": "154_wire.jpg",
            "rym": "https://rateyourmusic.com/release/album/wire/154/",
            "artist": "Wire",
            "album": "154"
        }
    ],
    "2025-01-12": [
        {
            "image": "resurrection_sadistic-intent.jpg",
            "rym": "https://rateyourmusic.com/release/ep/sadistic-intent/resurrection/",
            "artist": "Sadistic Intent",
            "album": "Resurrection"
        }
    ],
    "2025-01-13": [
        {
            "image": "roxy-music_roxy-music.jpg",
            "rym": "https://rateyourmusic.com/release/album/roxy-music/roxy-music/",
            "artist": "Roxy Music",
            "album": "Roxy Music"
        }
    ],
    "2025-01-14": [
        {
            "image": "embrace_embrace.jpg",
            "rym": "https://rateyourmusic.com/release/album/embrace/embrace-1/",
            "artist": "Embrace",
            "album": "Embrace"
        }
    ],
    "2025-01-15": [
        {
            "image": "gateways-to-annihilation_morbid-angel.jpg",
            "rym": "https://rateyourmusic.com/release/album/morbid-angel/gateways-to-annihilation/",
            "artist": "Morbid Angel",
            "album": "Gateways to Annihilation"
        }
    ],
    "2025-01-16": [
        {
            "image": "formulas-fatal-to-the-flesh_morbid-angel.jpg",
            "rym": "https://rateyourmusic.com/release/album/morbid-angel/formulas-fatal-to-the-flesh/",
            "artist": "Morbid Angel",
            "album": "Formulas Fatal to the Flesh"
        }
    ],
    "2025-01-17": [
        {
            "image": "war-master_bolt-thrower.jpg",
            "rym": "https://rateyourmusic.com/release/album/bolt-thrower/war-master/",
            "artist": "Bolt Thrower",
            "album": "War Master"
        }
    ],
    "2025-01-18": [
        {
            "image": "american-nervoso_botch.jpg",
            "rym": "https://rateyourmusic.com/release/album/botch/american-nervoso/",
            "artist": "Botch",
            "album": "American Nervoso"
        }
    ],
    "2025-01-19": [
        {
            "image": "an-anthology-of-dead-ends_botch.jpg",
            "rym": "https://rateyourmusic.com/release/ep/botch/an-anthology-of-dead-ends/",
            "artist": "Botch",
            "album": "An Anthology of Dead Ends"
        }
    ],
    "2025-01-20": [
        {
            "image": "youth-of-america_wipers.jpg",
            "rym": "https://rateyourmusic.com/release/album/wipers/youth-of-america/",
            "artist": "Wipers",
            "album": "Youth of America"
        }
    ],
    "2025-01-21": [
        {
            "image": "mass-vi_amenra.jpg",
            "rym": "https://rateyourmusic.com/release/album/amenra/mass-vi/",
            "artist": "Amenra",
            "album": "Mass VI"
        }
    ],
    "2025-01-22": [
        {
            "image": "orchid_orchid.jpg",
            "rym": "https://rateyourmusic.com/release/album/orchid/orchid/",
            "artist": "Orchid",
            "album": "Orchid"
        }
    ],
    "2025-01-23": [
        {
            "image": "horrified_repulsion.jpg",
            "rym": "https://rateyourmusic.com/release/album/repulsion/horrified/",
            "artist": "Repulsion",
            "album": "Horrified"
        }
    ],
    "2025-01-24": [
        {
            "image": "floral-green_title-fight.jpg",
            "rym": "https://rateyourmusic.com/release/album/title-fight/floral-green/",
            "artist": "Title Fight",
            "album": "Floral Green"
        }
    ],
    "2025-01-25": [
        {
            "image": "shed_title-fight.jpg",
            "rym": "https://rateyourmusic.com/release/album/title-fight/shed/",
            "artist": "Title Fight",
            "album": "Shed"
        }
    ],
    "2025-01-26": [
        {
            "image": "buster_admiral-angry.jpg",
            "rym": "https://rateyourmusic.com/release/album/admiral-angry/buster/",
            "artist": "Admiral Angry",
            "album": "Buster"
        }
    ],
    "2025-01-27": [
        {
            "image": "three-cheers-for-sweet-revenge_my-chemical-romance.jpg",
            "rym": "https://rateyourmusic.com/release/album/my-chemical-romance/three-cheers-for-sweet-revenge/",
            "artist": "My Chemical Romance",
            "album": "Three Cheers for Sweet Revenge"
        }
    ],
    "2025-01-28": [
        {
            "image": "the-black-parade_my-chemical-romance.jpg",
            "rym": "https://rateyourmusic.com/release/album/my-chemical-romance/the-black-parade/",
            "artist": "My Chemical Romance",
            "album": "The Black Parade"
        }
    ],
    "2025-01-29": [
        {
            "image": "songs-to-scream-at-the-sun_have-heart.jpg",
            "rym": "https://rateyourmusic.com/release/album/have-heart/songs-to-scream-at-the-sun/",
            "artist": "Have Heart",
            "album": "Songs to Scream at the Sun"
        }
    ],
    "2025-01-30": [
        {
            "image": "didn't-it-rain_songs:-ohia.jpg",
            "rym": "https://rateyourmusic.com/release/album/songs-ohia/didnt-it-rain/",
            "artist": "Songs: Ohia",
            "album": "Didn't It Rain"
        }
    ],
    "2025-01-31": [
        {
            "image": "dots-and-loops_stereolab.jpg",
            "rym": "https://rateyourmusic.com/release/album/stereolab/dots-and-loops/",
            "artist": "Stereolab",
            "album": "Dots and Loops"
        }
    ],
    "2025-02-01": [
        {
            "image": "chairs-missing_wire.jpg",
            "rym": "https://rateyourmusic.com/release/album/wire/chairs-missing/",
            "artist": "Wire",
            "album": "Chairs Missing"
        }
    ],
    "2025-02-02": [
        {
            "image": "knocknarea_maruja.jpg",
            "rym": "https://rateyourmusic.com/release/ep/maruja/knocknarea/",
            "artist": "Maruja",
            "album": "Knocknarea"
        }
    ],
    "2025-02-03": [
        {
            "image": "connla's-well_maruja.jpg",
            "rym": "https://rateyourmusic.com/release/ep/maruja/connlas-well/",
            "artist": "Maruja",
            "album": "Connla's Well"
        }
    ],
    "2025-02-04": [
        {
            "image": "bocanada_gustavo-cerati.jpg",
            "rym": "https://rateyourmusic.com/release/album/gustavo-cerati/bocanada/",
            "artist": "Gustavo Cerati",
            "album": "Bocanada"
        }
    ],
    "2025-02-05": [
        {
            "image": "the-velvet-rope_janet-jackson.jpg",
            "rym": "https://rateyourmusic.com/release/album/janet/the-velvet-rope/",
            "artist": "Janet Jackson",
            "album": "The Velvet Rope"
        }
    ],
    "2025-02-06": [
        {
            "image": "rain-upon-the-impure_the-ruins-of-beverast.jpg",
            "rym": "https://rateyourmusic.com/release/album/the-ruins-of-beverast/rain-upon-the-impure/",
            "artist": "The Ruins of Beverast",
            "album": "Rain Upon the Impure"
        }
    ],
    "2025-02-07": [
        {
            "image": "blue-train_john-coltrane.jpg",
            "rym": "https://rateyourmusic.com/release/album/john-coltrane/blue-train/",
            "artist": "John Coltrane",
            "album": "Blue Train"
        }
    ],
    "2025-02-08": [
        {
            "image": "brat_charlie-xcx.jpg",
            "rym": "https://rateyourmusic.com/release/album/charli-xcx/brat/",
            "artist": "Charlie XCX",
            "album": "Brat"
        }
    ],
    "2025-02-09": [
        {
            "image": "more-gunfighter-ballads-and-trail-songs_marty-robbins.jpg",
            "rym": "https://rateyourmusic.com/release/album/marty-robbins/more-gunfighter-ballads-and-trail-songs/",
            "artist": "Marty Robbins",
            "album": "More Gunfighter Ballads and Trail Songs"
        }
    ],
    "2025-02-10": [
        {
            "image": "the-rise-and-fall-of-a-midwest-princess_chappell-roan.jpg",
            "rym": "https://rateyourmusic.com/release/album/chappell-roan/the-rise-and-fall-of-a-midwest-princess/",
            "artist": "Chappell Roan",
            "album": "The Rise and Fall of a Midwest Princess "
        }
    ],
    "2025-02-11": [
        {
            "image": "attempted-martyr_prostitute.jpg",
            "rym": "https://rateyourmusic.com/release/album/prostitute/attempted-martyr/",
            "artist": "Prostitute",
            "album": "Attempted Martyr"
        }
    ],
    "2025-02-12": [
        {
            "image": "giving-birth-to-thunder_indian-summer.jpg",
            "rym": "https://rateyourmusic.com/release/comp/indian-summer/giving-birth-to-thunder/",
            "artist": "Indian Summer",
            "album": "Giving Birth to Thunder"
        }
    ],
    "2025-02-13": [
        {
            "image": "hejira_joni-mitchell.jpg",
            "rym": "https://rateyourmusic.com/release/album/joni-mitchell/hejira/",
            "artist": "Joni Mitchell",
            "album": "Hejira"
        }
    ],
    "2025-02-14": [
        {
            "image": "dust-bowl-ballads_woody-guthrie.jpg",
            "rym": "https://rateyourmusic.com/release/comp/woody-guthrie/dust-bowl-ballads/",
            "artist": "Woody Guthrie",
            "album": "Dust Bowl Ballads"
        }
    ],
    "2025-02-15": [
        {
            "image": "cave-world_viagra-boys.jpg",
            "rym": "https://rateyourmusic.com/release/album/viagra-boys/cave-world/",
            "artist": "Viagra Boys",
            "album": "Cave World"
        }
    ],
    "2025-02-16": [
        {
            "image": "if-god-only-knew-the-rest-were-dead_disembodied.jpg",
            "rym": "https://rateyourmusic.com/release/ep/disembodied/if-god-only-knew-the-rest-were-dead/",
            "artist": "Disembodied",
            "album": "If God Only Knew the Rest Were Dead"
        }
    ],
    "2025-02-17": [
        {
            "image": "ladies-of-the-canyon_joni-mitchell.jpg",
            "rym": "https://rateyourmusic.com/release/album/joni-mitchell/ladies-of-the-canyon/",
            "artist": "Joni Mitchell",
            "album": "Ladies of the Canyon"
        }
    ],
    "2025-02-18": [
        {
            "image": "7-songs-for-spiders_dax-riggs.jpg",
            "rym": "https://rateyourmusic.com/release/album/dax-riggs/7-songs-for-spiders/",
            "artist": "Dax Riggs",
            "album": "7 Songs for Spiders"
        }
    ],
    "2025-02-19": [
        {
            "image": "to-be-continued_isaac-hayes.jpg",
            "rym": "https://rateyourmusic.com/release/album/isaac-hayes/_to-be-continued/",
            "artist": "Isaac Hayes",
            "album": "...To Be Continued"
        }
    ],
    "2025-02-20": [
        {
            "image": "thunder-perfect-mind_current-93.jpg",
            "rym": "https://rateyourmusic.com/release/album/current-93/thunder-perfect-mind/",
            "artist": "Current 93",
            "album": "Thunder Perfect Mind"
        }
    ],
    "2025-02-21": [
        {
            "image": "sleep-has-his-house_current-93.jpg",
            "rym": "https://rateyourmusic.com/release/album/current-ninety-three/sleep-has-his-house/",
            "artist": "Current 93",
            "album": "Sleep Has His House"
        }
    ],
    "2025-02-22": [
        {
            "image": "all-the-pretty-little-horses_current-93.jpg",
            "rym": "https://rateyourmusic.com/release/album/current-93/all-the-pretty-little-horses/",
            "artist": "Current 93",
            "album": "All the Pretty Little Horses"
        }
    ],
    "2025-02-23": [
        {
            "image": "gorilla-biscuits_gorilla-biscuits.jpg",
            "rym": "https://rateyourmusic.com/release/ep/gorilla-biscuits/gorilla-biscuits/",
            "artist": "Gorilla Biscuits",
            "album": "Gorilla Biscuits"
        }
    ],
    "2025-02-24": [
        {
            "image": "soft-black-stars_current-93.jpg",
            "rym": "https://rateyourmusic.com/release/album/currentninetythree/soft-black-stars/",
            "artist": "Current 93",
            "album": "Soft Black Stars"
        }
    ],
    "2025-02-25": [
        {
            "image": "petitioning-the-empty-sky_converge.jpg",
            "rym": "https://rateyourmusic.com/release/album/converge/petitioning-the-empty-sky/",
            "artist": "Converge",
            "album": "Petitioning the Empty Sky"
        }
    ],
    "2025-02-26": [
        {
            "image": "when-forever-comes-crashing_converge.jpg",
            "rym": "https://rateyourmusic.com/release/album/converge/when-forever-comes-crashing-3/",
            "artist": "Converge",
            "album": "When Forever Comes Crashing"
        }
    ],
    "2025-02-27": [
        {
            "image": "middle-spoon_cheekface.jpg",
            "rym": "https://rateyourmusic.com/release/album/cheekface/middle-spoon/",
            "artist": "Cheekface",
            "album": "Middle Spoon"
        }
    ],
    "2025-02-28": [
        {
            "image": "i-want-to-be-there_sadness.jpg",
            "rym": "https://rateyourmusic.com/release/album/sadness/i-want-to-be-there/",
            "artist": "Sadness",
            "album": "I Want to be There"
        }
    ],
    "2025-03-01": [
        {
            "image": "scott-4_scott-walker.jpg",
            "rym": "https://rateyourmusic.com/release/album/scott-engel/scott-4/",
            "artist": "Scott Walker",
            "album": "Scott 4"
        }
    ],
    "2025-03-02": [
        {
            "image": "godflesh_godflesh.jpg",
            "rym": "https://rateyourmusic.com/release/ep/godflesh/godflesh/",
            "artist": "Godflesh",
            "album": "Godflesh"
        }
    ],
    "2025-03-03": [
        {
            "image": "streetcleaner_godflesh.jpg",
            "rym": "https://rateyourmusic.com/release/album/godflesh/streetcleaner/",
            "artist": "Godflesh",
            "album": "Streetcleaner"
        }
    ],
    "2025-03-04": [
        {
            "image": "diabolical-conquest_incantation.jpg",
            "rym": "https://rateyourmusic.com/release/album/incantation/diabolical-conquest/",
            "artist": "Incantation",
            "album": "Diabolical Conquest"
        }
    ],
    "2025-03-05": [
        {
            "image": "fires-within-fires_neurosis.jpg",
            "rym": "https://rateyourmusic.com/release/album/neurosis/fires-within-fires/",
            "artist": "Neurosis",
            "album": "Fires Within Fires"
        }
    ],
    "2025-03-06": [
        {
            "image": "we-buy-diabetic-test-strips_armand-hammer.jpg",
            "rym": "https://rateyourmusic.com/release/album/armand-hammer/we-buy-diabetic-test-strips/",
            "artist": "Armand Hammer",
            "album": "We Buy Diabetic Test Strips "
        }
    ],
    "2025-03-07": [
        {
            "image": "highway-61-revisited_bob-dylan.jpg",
            "rym": "https://rateyourmusic.com/release/album/bob-dylan/highway-61-revisited/",
            "artist": "Bob Dylan",
            "album": "Highway 61 Revisited "
        }
    ],
    "2025-03-08": [
        {
            "image": "clandestine_entombed.jpg",
            "rym": "https://rateyourmusic.com/release/album/entombed/clandestine/",
            "artist": "Entombed",
            "album": "Clandestine"
        }
    ],
    "2025-03-09": [
        {
            "image": "no-wings-to-speak-of_hopesfall.jpg",
            "rym": "https://rateyourmusic.com/release/ep/hopesfall/no-wings-to-speak-of/",
            "artist": "Hopesfall",
            "album": "No Wings to Speak Of "
        }
    ],
    "2025-03-10": [
        {
            "image": "wolverine-blues_entombed.jpg",
            "rym": "https://rateyourmusic.com/release/album/entombed/wolverine-blues/",
            "artist": "Entombed",
            "album": "Wolverine Blues "
        }
    ],
    "2025-03-11": [
        {
            "image": "salt-sermon_missouri-executive-order-44.jpg",
            "rym": "https://rateyourmusic.com/release/album/missouri-executive-order-44/salt-sermon/",
            "artist": "Missouri Executive Order 44",
            "album": "Salt Sermon"
        }
    ],
    "2025-03-12": [
        {
            "image": "artaud_pescado-rabioso.jpg",
            "rym": "https://rateyourmusic.com/release/album/pescado-rabioso/artaud/",
            "artist": "Pescado Rabioso",
            "album": "Artaud"
        }
    ],
    "2025-03-13": [
        {
            "image": "seventeen-dead-in-caldwell-county_missouri-executive-order-44.jpg",
            "rym": "https://rateyourmusic.com/release/ep/missouri-executive-order-44/seventeen-dead-in-caldwell-county/",
            "artist": "Missouri Executive Order 44",
            "album": "Seventeen Dead in Caldwell County"
        }
    ],
    "2025-03-14": [
        {
            "image": "broken-glass_crowbar.jpg",
            "rym": "https://rateyourmusic.com/release/album/crowbar/broken-glass/",
            "artist": "Crowbar",
            "album": "Broken Glass"
        }
    ],
    "2025-03-15": [
        {
            "image": "ritual-music-for-the-true-clochard_urfaust.jpg",
            "rym": "https://rateyourmusic.com/release/comp/urfaust/ritual-music-for-the-true-clochard/",
            "artist": "Urfaust",
            "album": "Ritual Music for the True Clochard"
        }
    ],
    "2025-03-16": [
        {
            "image": "odelay_beck.jpg",
            "rym": "https://rateyourmusic.com/release/album/beck/odelay/",
            "artist": "Beck",
            "album": "Odelay"
        }
    ],
    "2025-03-17": [
        {
            "image": "agaetis-byrjun_sigur-ros.jpg",
            "rym": "https://rateyourmusic.com/release/album/sigur-ros/agaetis-byrjun/",
            "artist": "Sigur Rós",
            "album": "Ágætis byrjun"
        }
    ],
    "2025-03-18": [
        {
            "image": "アダンの風-(windswept-adan)_青葉市子-(ichiko-aoba).jpg",
            "rym": "https://rateyourmusic.com/release/album/%E9%9D%92%E8%91%89%E5%B8%82%E5%AD%90/%E3%82%A2%E3%83%80%E3%83%B3%E3%81%AE%E9%A2%A8/",
            "artist": "青葉市子 (Ichiko Aoba)",
            "album": "アダンの風 (Windswept Adan)"
        }
    ],
    "2025-03-19": [
        {
            "image": "let-it-be_the-replacements.jpg",
            "rym": "https://rateyourmusic.com/release/album/the-replacements/let-it-be/",
            "artist": "The Replacements",
            "album": "Let it Be"
        }
    ],
    "2025-03-20": [
        {
            "image": "still_nine-inch-nails.jpg",
            "rym": "https://rateyourmusic.com/release/album/nine-inch-nails/still/",
            "artist": "Nine Inch Nails",
            "album": "Still"
        }
    ],
    "2025-03-21": [
        {
            "image": "a-celestial-ballad_dawn-of-orion.jpg",
            "rym": "https://rateyourmusic.com/release/comp/dawn-of-orion/a-celestial-ballad/",
            "artist": "Dawn of Orion",
            "album": "A Celestial Ballad"
        }
    ],
    "2025-03-22": [
        {
            "image": "on-top-of-the-world_8ball-&-mjg.jpg",
            "rym": "https://rateyourmusic.com/release/album/eightball-and-mjg/on-top-of-the-world/",
            "artist": "8Ball & MJG",
            "album": "On Top of the World"
        }
    ],
    "2025-03-23": [
        {
            "image": "hammerheart_bathory.jpg",
            "rym": "https://rateyourmusic.com/release/album/bathory/hammerheart/",
            "artist": "Bathory",
            "album": "Hammerheart"
        }
    ],
    "2025-03-24": [
        {
            "image": "tortured-existence_demolition-hammer.jpg",
            "rym": "https://rateyourmusic.com/release/album/demolition-hammer/tortured-existence/",
            "artist": "Demolition Hammer",
            "album": "Tortured Existence"
        }
    ],
    "2025-03-25": [
        {
            "image": "bathory_bathory.jpg",
            "rym": "https://rateyourmusic.com/release/album/bathory/bathory/",
            "artist": "Bathory",
            "album": "Bathory"
        }
    ],
    "2025-03-26": [
        {
            "image": "die-kreuzen_die-kreuzen.jpg",
            "rym": "https://rateyourmusic.com/release/album/die-kreuzen/die-kreuzen-3/",
            "artist": "Die Kreuzen",
            "album": "Die Kreuzen"
        }
    ],
    "2025-03-27": [
        {
            "image": "three-sided-tape-volume-one_lil-ugly-mane.jpg",
            "rym": "https://rateyourmusic.com/release/album/lil-ugly-mane/three-sided-tape-volume-one/",
            "artist": "Lil Ugly Mane",
            "album": "Three Sided Tape Volume One"
        }
    ],
    "2025-03-28": [
        {
            "image": "lonely-people-with-power_deafheaven.jpg",
            "rym": "https://rateyourmusic.com/release/album/deafheaven/lonely-people-with-power/",
            "artist": "Deafheaven",
            "album": "Lonely People With Power"
        }
    ],
    "2025-03-29": [
        {
            "image": "what-a-fucking-nightmare_the-chisel.jpg",
            "rym": "https://rateyourmusic.com/release/album/the-chisel/what-a-fucking-nightmare/",
            "artist": "The Chisel",
            "album": "What a Fucking Nightmare"
        }
    ],
    "2025-03-30": [
        {
            "image": "minecraft:-volume-beta_c418.jpg",
            "rym": "https://rateyourmusic.com/release/album/c418/minecraft-volume-beta/",
            "artist": "C418",
            "album": "Minecraft: Volume Beta"
        }
    ],
    "2025-03-31": [
        {
            "image": "comin'-out-hard_8ball-&-mjg.jpg",
            "rym": "https://rateyourmusic.com/release/album/eightball-and-mjg/comin-out-hard/",
            "artist": "8Ball & MJG",
            "album": "Comin' Out Hard"
        }
    ],
    "2025-04-01": [
        {
            "image": "10-years-gone_deafheaven.jpg",
            "rym": "https://rateyourmusic.com/release/additional/deafheaven/10-years-gone/",
            "artist": "Deafheaven",
            "album": "10 Years Gone"
        }
    ],
    "2025-04-02": [
        {
            "image": "playaz-circle_lil-ugly-mane.jpg",
            "rym": "https://rateyourmusic.com/release/mixtape/lil-ugly-mane/playaz-circle-1/",
            "artist": "Lil Ugly Mane",
            "album": "Playaz Circle"
        }
    ],
    "2025-04-03": [
        {
            "image": "twilight-of-the-gods_bathory.jpg",
            "rym": "https://rateyourmusic.com/release/album/bathory/twilight-of-the-gods/",
            "artist": "Bathory",
            "album": "Twilight of the Gods"
        }
    ],
    "2025-04-04": [
        {
            "image": "crooked-rain,-crooked-rain_pavement.jpg",
            "rym": "https://rateyourmusic.com/release/album/pavement/crooked-rain-crooked-rain-11/",
            "artist": "Pavement",
            "album": "Crooked Rain, Crooked Rain"
        }
    ],
    "2025-04-05": [
        {
            "image": "wowee-zowee_pavement.jpg",
            "rym": "https://rateyourmusic.com/release/album/pavement/wowee-zowee/",
            "artist": "Pavement",
            "album": "Wowee Zowee"
        }
    ],
    "2025-04-06": [
        {
            "image": "watery,-domestic_pavement.jpg",
            "rym": "https://rateyourmusic.com/release/ep/pavement/watery-domestic/",
            "artist": "Pavement",
            "album": "Watery, Domestic"
        }
    ],
    "2025-04-07": [
        {
            "image": "massive-conspiracy-against-all-life_leviathan.jpg",
            "rym": "https://rateyourmusic.com/release/album/leviathan/massive-conspiracy-against-all-life/",
            "artist": "Leviathan",
            "album": "Massive Conspiracy Against All Life"
        }
    ],
    "2025-04-08": [
        {
            "image": "far-away-from-the-sun_sacramentum.jpg",
            "rym": "https://rateyourmusic.com/release/album/sacramentum/far-away-from-the-sun-8/",
            "artist": "Sacramentum",
            "album": "Far Away From the Sun"
        }
    ],
    "2025-04-09": [
        {
            "image": "autumn-eternal_panopticon.jpg",
            "rym": "https://rateyourmusic.com/release/album/panopticon/autumn-eternal/",
            "artist": "Panopticon",
            "album": "Autumn Eternal"
        }
    ],
    "2025-04-10": [
        {
            "image": "kentucky_panopticon.jpg",
            "rym": "https://rateyourmusic.com/release/album/panopticon/kentucky/",
            "artist": "Panopticon",
            "album": "Kentucky"
        }
    ],
    "2025-04-11": [
        {
            "image": "a-l'ame-enflammee,-l'ame-constellee_gris.jpg",
            "rym": "https://rateyourmusic.com/release/album/gris/a-lame-enflammee-lame-constellee/",
            "artist": "Gris",
            "album": "À l'âme enflammée, l'âme constellée..."
        }
    ],
    "2025-04-12": [
        {
            "image": "civilisation-ii_kero-kero-bonito.jpg",
            "rym": "https://rateyourmusic.com/release/ep/kero-kero-bonito/civilisation-ii/",
            "artist": "Kero Kero Bonito",
            "album": "Civilisation II"
        }
    ],
    "2025-04-13": [
        {
            "image": "time-'n'-place_kero-kero-bonito.jpg",
            "rym": "https://rateyourmusic.com/release/album/kero-kero-bonito/time-n-place/",
            "artist": "Kero Kero Bonito",
            "album": "Time 'n' Place"
        }
    ],
    "2025-04-14": [
        {
            "image": "hordanes-land_enslaved.jpg",
            "rym": "https://rateyourmusic.com/release/ep/enslaved/hordanes-land/",
            "artist": "Enslaved",
            "album": "Hordanes Land"
        }
    ],
    "2025-04-15": [
        {
            "image": "bonito-generation_kero-kero-bonito.jpg",
            "rym": "https://rateyourmusic.com/release/album/kero-kero-bonito/bonito-generation/",
            "artist": "Kero Kero Bonito",
            "album": "Bonito Generation"
        }
    ],
    "2025-04-16": [
        {
            "image": "endless-detainment_serpent-column.jpg",
            "rym": "https://rateyourmusic.com/release/ep/serpent-column/endless-detainment/",
            "artist": "Serpent Column",
            "album": "Endless Detainment"
        }
    ],
    "2025-04-17": [
        {
            "image": "the-\"deep\"_soul-scream.jpg",
            "rym": "https://rateyourmusic.com/release/album/soul-scream/the-deep/",
            "artist": "Soul Scream",
            "album": "The \"Deep\""
        }
    ],
    "2025-04-18": [
        {
            "image": "tir-na-nog_maruja.jpg",
            "rym": "https://rateyourmusic.com/release/ep/maruja/tir-na-nog/",
            "artist": "Maruja",
            "album": "Tír na nÓg "
        }
    ],
    "2025-04-19": [
        {
            "image": "civilisation-i_kero-kero-bonito.jpg",
            "rym": "https://rateyourmusic.com/release/ep/kero-kero-bonito/civilisation-i/",
            "artist": "Kero Kero Bonito",
            "album": "Civilisation I"
        }
    ],
    "2025-04-20": [
        {
            "image": "totep_kero-kero-bonito.jpg",
            "rym": "https://rateyourmusic.com/release/ep/kero-kero-bonito/totep/",
            "artist": "Kero Kero Bonito",
            "album": "TOTEP"
        }
    ],
    "2025-04-21": [
        {
            "image": "mercurial-world_magdalena-bay.jpg",
            "rym": "https://rateyourmusic.com/release/album/magdalena-bay/mercurial-world/",
            "artist": "Magdalena Bay",
            "album": "Mercurial World"
        }
    ],
    "2025-04-22": [
        {
            "image": "the-ultra-violence_death-angel.jpg",
            "rym": "https://rateyourmusic.com/release/album/death-angel/the-ultra-violence/",
            "artist": "Death Angel",
            "album": "The Ultra-Violence"
        }
    ],
    "2025-04-23": [
        {
            "image": "entertainment!_gang-of-four.jpg",
            "rym": "https://rateyourmusic.com/release/album/gang-of-four/entertainment/",
            "artist": "Gang of Four",
            "album": "Entertainment!"
        }
    ],
    "2025-04-24": [
        {
            "image": "presence_mgla.jpg",
            "rym": "https://rateyourmusic.com/release/ep/mgla/presence/",
            "artist": "Mgła",
            "album": "Presence"
        }
    ],
    "2025-04-25": [
        {
            "image": "those-who-caress-the-pale_ved-buens-ende.jpg",
            "rym": "https://rateyourmusic.com/release/ep/ved-buens-ende/those-who-caress-the-pale/",
            "artist": "Ved Buens Ende.....",
            "album": "Those Who Caress the Pale"
        }
    ],
    "2025-04-26": [
        {
            "image": "sap_alice-in-chains.jpg",
            "rym": "https://rateyourmusic.com/release/ep/alice-in-chains/sap/",
            "artist": "Alice in Chains",
            "album": "Sap"
        }
    ],
    "2025-04-27": [
        {
            "image": "brighten-the-corners_pavement.jpg",
            "rym": "https://rateyourmusic.com/release/album/pavement/brighten-the-corners/",
            "artist": "Pavement",
            "album": "Brighten the Corners"
        }
    ],
    "2025-04-28": [
        {
            "image": "vikingligr-veldi_enslaved.jpg",
            "rym": "https://rateyourmusic.com/release/album/enslaved/vikingligr-veldi/",
            "artist": "Enslaved",
            "album": "Vikingligr Veldi"
        }
    ],
    "2025-04-29": [
        {
            "image": "axioma-ethica-odini_enslaved.jpg",
            "rym": "https://rateyourmusic.com/release/album/enslaved/axioma-ethica-odini/",
            "artist": "Enslaved",
            "album": "Axioma Ethica Odini"
        }
    ],
    "2025-04-30": [
        {
            "image": "viagr-aboys_viagra-boys.jpg",
            "rym": "https://rateyourmusic.com/release/album/viagra-boys/viagr-aboys/",
            "artist": "Viagra Boys",
            "album": "viagr aboys"
        }
    ],
    "2025-05-01": [
        {
            "image": "for-kunsten-maa-vi-evig-vike_kvist.jpg",
            "rym": "https://rateyourmusic.com/release/album/kvist/for-kunsten-maa-vi-evig-vike/",
            "artist": "Kvist",
            "album": "For Kunsten Maa Vi Evig Vike"
        }
    ],
    "2025-05-02": [
        {
            "image": "motherfucker,-i-am-both:-\"amen\"-and-\"hallelujah\"_shearling.jpg",
            "rym": "https://rateyourmusic.com/release/album/shearling/motherfucker-i-am-both-amen-and-hallelujah/",
            "artist": "Shearling",
            "album": "Motherfucker, I Am Both: \"Amen\" and \"Hallelujah\"..."
        }
    ],
    "2025-05-03": [
        {
            "image": "autumn-aurora_drudkh.jpg",
            "rym": "https://rateyourmusic.com/release/album/drudkh/autumn-aurora/",
            "artist": "Drudkh",
            "album": "Autumn Aurora"
        }
    ],
    "2025-05-04": [
        {
            "image": "malibu-ken_malibu-ken.jpg",
            "rym": "https://rateyourmusic.com/release/album/malibu-ken/malibu-ken/",
            "artist": "Malibu Ken",
            "album": "Malibu Ken"
        }
    ],
    "2025-05-05": [
        {
            "image": "aethiopes_billy-woods.jpg",
            "rym": "https://rateyourmusic.com/release/album/billy-woods/aethiopes/",
            "artist": "Billy Woods",
            "album": "Aethiopes"
        }
    ],
    "2025-05-06": [
        {
            "image": "sonoran-depravation_gatecreeper.jpg",
            "rym": "https://rateyourmusic.com/release/album/gatecreeper/sonoran-depravation/",
            "artist": "Gatecreeper",
            "album": "Sonoran Depravation"
        }
    ],
    "2025-05-07": [
        {
            "image": "schnee_paysage-d'hiver.jpg",
            "rym": "https://rateyourmusic.com/release/comp/paysage-dhiver/schnee/",
            "artist": "Paysage d'Hiver",
            "album": "Schnee"
        }
    ],
    "2025-05-08": [
        {
            "image": "93696_liturgy.jpg",
            "rym": "https://rateyourmusic.com/release/album/liturgy/93696/",
            "artist": "Liturgy",
            "album": "93696"
        }
    ],
    "2025-05-09": [
        {
            "image": "golliwog_billy-woods.jpg",
            "rym": "https://rateyourmusic.com/release/album/billy-woods/golliwog/",
            "artist": "Billy Woods",
            "album": "Golliwog"
        }
    ],
    "2025-05-10": [
        {
            "image": "grin_coroner.jpg",
            "rym": "https://rateyourmusic.com/release/album/coroner/grin/",
            "artist": "Coroner",
            "album": "Grin"
        }
    ],
    "2025-05-11": [
        {
            "image": "master-killer_merauder.jpg",
            "rym": "https://rateyourmusic.com/release/album/merauder/master-killer-2/",
            "artist": "Merauder",
            "album": "Master Killer"
        }
    ],
    "2025-05-12": [
        {
            "image": "planisphere_justice.jpg",
            "rym": "https://rateyourmusic.com/release/ep/justice/planisphere/",
            "artist": "Justice",
            "album": "Planisphère"
        }
    ],
    "2025-05-13": [
        {
            "image": "everyone-asked-about-you_everyone-asked-about-you.jpg",
            "rym": "https://rateyourmusic.com/release/ep/everyone-asked-about-you/everyone-asked-about-you/",
            "artist": "Everyone Asked About You",
            "album": "Everyone Asked About You"
        }
    ],
    "2025-05-14": [
        {
            "image": "diadem-of-12-stars_wolves-in-the-throne-room.jpg",
            "rym": "https://rateyourmusic.com/release/album/wolves-in-the-throne-room/diadem-of-12-stars/",
            "artist": "Wolves In The Throne Room",
            "album": "Diadem Of 12 Stars"
        }
    ],
    "2025-05-15": [
        {
            "image": "ashes-against-the-grain_agalloch.jpg",
            "rym": "https://rateyourmusic.com/release/album/agalloch/ashes-against-the-grain/",
            "artist": "Agalloch",
            "album": "Ashes Against The Grain"
        }
    ],
    "2025-05-16": [
        {
            "image": "forgotten-legends_drudkh.jpg",
            "rym": "https://rateyourmusic.com/release/album/drudkh/forgotten-legends/",
            "artist": "Drudkh",
            "album": "Forgotten Legends"
        }
    ],
    "2025-05-17": [
        {
            "image": "the-voice-of-steel_nokturnal-mortum.jpg",
            "rym": "https://rateyourmusic.com/release/album/nokturnal-mortum/%D0%B3%D0%BE%D0%BB%D0%BE%D1%81-%D1%81%D1%82%D0%B0%D0%BB%D1%96/",
            "artist": "Nokturnal Mortum",
            "album": "The Voice of Steel"
        }
    ],
    "2025-05-18": [
        {
            "image": "sis-(soft-is-strong)_katseye.jpg",
            "rym": "https://rateyourmusic.com/release/ep/katseye/sis-soft-is-strong/",
            "artist": "Katseye",
            "album": "SIS (Soft is Strong) "
        }
    ],
    "2025-05-19": [
        {
            "image": "unholy-cult_immolation.jpg",
            "rym": "https://rateyourmusic.com/release/album/immolation/unholy-cult/",
            "artist": "Immolation",
            "album": "Unholy Cult"
        }
    ],
    "2025-05-20": [
        {
            "image": "the-river_bruce-springsteen.jpg",
            "rym": "https://rateyourmusic.com/release/album/bruce-springsteen/the-river/",
            "artist": "Bruce Springsteen",
            "album": "The River"
        }
    ],
    "2025-05-21": [
        {
            "image": "heavy-heavy_young-fathers.jpg",
            "rym": "https://rateyourmusic.com/release/album/young-fathers/heavy-heavy/",
            "artist": "Young Fathers",
            "album": "Heavy Heavy"
        }
    ],
    "2025-05-22": [
        {
            "image": "oil-of-every-pearl's-un-insides_sophie.jpg",
            "rym": "https://rateyourmusic.com/release/album/sophie/oil-of-every-pearls-un-insides/",
            "artist": "Sophie",
            "album": "Oil of Every Pearl's Un-Insides"
        }
    ],
    "2025-05-23": [
        {
            "image": "kelle-surut-soi_havukruunu.jpg",
            "rym": "https://rateyourmusic.com/release/album/havukruunu/kelle-surut-soi/",
            "artist": "Havukruunu",
            "album": "Kelle Surut Soi"
        }
    ],
    "2025-05-24": [
        {
            "image": "tulimyrsky_moonsorrow.jpg",
            "rym": "https://rateyourmusic.com/release/ep/moonsorrow/tulimyrsky_ep/",
            "artist": "Moonsorrow",
            "album": "Tulimyrsky"
        }
    ],
    "2025-05-25": [
        {
            "image": "akuma-no-uta_boris.jpg",
            "rym": "https://rateyourmusic.com/release/album/boris/%E3%81%82%E3%81%8F%E3%81%BE%E3%81%AE%E3%81%86%E3%81%9F/",
            "artist": "Boris",
            "album": "Akuma no uta"
        }
    ],
    "2025-05-26": [
        {
            "image": "an-anatomy-of-the-beast_intestine-baalism.jpg",
            "rym": "https://rateyourmusic.com/release/album/intestine-baalism/an-anatomy-of-the-beast/",
            "artist": "Intestine Baalism",
            "album": "An Anatomy Of The Beast"
        }
    ],
    "2025-05-27": [
        {
            "image": "banquet-in-the-darkness_intestine-baalism.jpg",
            "rym": "https://rateyourmusic.com/release/album/intestine-baalism/banquet-in-the-darkness/",
            "artist": "Intestine Baalism",
            "album": "Banquet In The Darkness"
        }
    ],
    "2025-05-28": [
        {
            "image": "purgatory-afterglow_edge-of-sanity.jpg",
            "rym": "https://rateyourmusic.com/release/album/edge-of-sanity/purgatory-afterglow-3/",
            "artist": "Edge Of Sanity",
            "album": "Purgatory Afterglow"
        }
    ],
    "2025-05-29": [
        {
            "image": "converging-ages_inanna.jpg",
            "rym": "https://rateyourmusic.com/release/album/inanna/converging-ages/",
            "artist": "Inanna",
            "album": "Converging Ages"
        }
    ],
    "2025-05-30": [
        {
            "image": "transfigured-in-a-thousand-delusions_inanna.jpg",
            "rym": "https://rateyourmusic.com/release/album/inanna/transfigured-in-a-thousand-delusions/",
            "artist": "Inanna",
            "album": "Transfigured In A Thousand Delusions"
        }
    ],
    "2025-05-31": [
        {
            "image": "whoracle_in-flames.jpg",
            "rym": "https://rateyourmusic.com/release/album/in-flames/whoracle/",
            "artist": "In Flames",
            "album": "Whoracle"
        }
    ],
    "2025-06-01": [
        {
            "image": "oracle-moon_garden-of-shadows.jpg",
            "rym": "https://rateyourmusic.com/release/album/garden-of-shadows/oracle-moon/",
            "artist": "Garden Of Shadows",
            "album": "Oracle Moon"
        }
    ],
    "2025-06-02": [
        {
            "image": "colony_in-flames.jpg",
            "rym": "https://rateyourmusic.com/release/album/in-flames/colony/",
            "artist": "In Flames",
            "album": "Colony"
        }
    ],
    "2025-06-03": [
        {
            "image": "clayman_in-flames.jpg",
            "rym": "https://rateyourmusic.com/release/album/in-flames/clayman/",
            "artist": "In Flames",
            "album": "Clayman"
        }
    ],
    "2025-06-04": [
        {
            "image": "the-gallery_dark-tranquillity.jpg",
            "rym": "https://rateyourmusic.com/release/album/dark-tranquillity/the-gallery/",
            "artist": "Dark Tranquillity",
            "album": "The Gallery"
        }
    ],
    "2025-06-05": [
        {
            "image": "avlivsritualer_vanvidd.jpg",
            "rym": "https://rateyourmusic.com/release/album/vanvidd/avlivsritualer/",
            "artist": "Vanvidd",
            "album": "Avlivsritualer"
        }
    ],
    "2025-06-06": [
        {
            "image": "black-hole-superette_aesop-rock.jpg",
            "rym": "https://rateyourmusic.com/release/album/aesop-rock/black-hole-superette/",
            "artist": "Aesop Rock",
            "album": "Black Hole Superette"
        }
    ],
    "2025-06-07": [
        {
            "image": "ultimate-instinct_intestine-baalism.jpg",
            "rym": "https://rateyourmusic.com/release/album/intestine-baalism/ultimate-instinct/",
            "artist": "Intestine Baalism",
            "album": "Ultimate Instinct"
        }
    ],
    "2025-06-08": [
        {
            "image": "internal-flight_estas-tonne.jpg",
            "rym": "https://rateyourmusic.com/release/album/estas-tonne/internal-flight/",
            "artist": "Estas Tonne",
            "album": "Internal Flight"
        }
    ],
    "2025-06-09": [
        {
            "image": "winters-gate_insomnium.jpg",
            "rym": "https://rateyourmusic.com/release/album/insomnium/winters-gate/",
            "artist": "Insomnium",
            "album": "Winters Gate"
        }
    ],
    "2025-06-10": [
        {
            "image": "above-the-weeping-world_insomnium.jpg",
            "rym": "https://rateyourmusic.com/release/album/insomnium/above-the-weeping-world/",
            "artist": "Insomnium",
            "album": "Above The Weeping World"
        }
    ],
    "2025-06-11": [
        {
            "image": "pet-sounds_the-beach-boys.jpg",
            "rym": "https://rateyourmusic.com/release/album/the-beach-boys/pet-sounds/",
            "artist": "The Beach Boys",
            "album": "Pet Sounds"
        }
    ],
    "2025-06-12": [
        {
            "image": "abigail_king-diamond.jpg",
            "rym": "https://rateyourmusic.com/release/album/king-diamond/abigail/",
            "artist": "King Diamond",
            "album": "Abigail"
        }
    ],
    "2025-06-13": [
        {
            "image": "conspiracy_king-diamond.jpg",
            "rym": "https://rateyourmusic.com/release/album/king-diamond/conspiracy/",
            "artist": "King Diamond",
            "album": "Conspiracy"
        }
    ],
    "2025-06-14": [
        {
            "image": "moontower_dan-swano.jpg",
            "rym": "https://rateyourmusic.com/release/album/dan-swano/moontower/",
            "artist": "Dan Swano",
            "album": "Moontower"
        }
    ],
    "2025-06-15": [
        {
            "image": "vii:-sturm-und-drang_lamb-of-god.jpg",
            "rym": "https://rateyourmusic.com/release/album/lamb-of-god/vii-sturm-und-drang/",
            "artist": "Lamb Of God",
            "album": "VII: Sturm und Drang "
        }
    ],
    "2025-06-16": [
        {
            "image": "omens_lamb-of-god.jpg",
            "rym": "https://rateyourmusic.com/release/album/lamb-of-god/omens/",
            "artist": "Lamb Of God",
            "album": "Omens"
        }
    ],
    "2025-06-17": [
        {
            "image": "you'd-prefer-an-astronaut_hum.jpg",
            "rym": "https://rateyourmusic.com/release/album/hum/youd-prefer-an-astronaut/",
            "artist": "Hum",
            "album": "You'd Prefer an Astronaut "
        }
    ],
    "2025-06-18": [
        {
            "image": "with-oden-on-our-side_amon-amarth.jpg",
            "rym": "https://rateyourmusic.com/release/album/amon-amarth/with-oden-on-our-side/",
            "artist": "Amon Amarth",
            "album": "With Oden On Our Side"
        }
    ]
}